mech_client/__init__.py
mech_client/abis/AgentMech.json
mech_client/abis/AgentRegistry.json
mech_client/abis/AgreementStoreManager.base.json
mech_client/abis/AgreementStoreManager.gnosis.json
mech_client/abis/BalanceTrackerFixedPriceNative.json
mech_client/abis/BalanceTrackerFixedPriceToken.json
mech_client/abis/BalanceTrackerNvmSubscriptionNative.json
mech_client/abis/BalanceTrackerNvmSubscriptionToken.json
mech_client/abis/ComplementaryServiceMetadata.json
mech_client/abis/DIDRegistry.base.json
mech_client/abis/DIDRegistry.gnosis.json
mech_client/abis/EscrowPaymentCondition.base.json
mech_client/abis/EscrowPaymentCondition.gnosis.json
mech_client/abis/IERC1155.json
mech_client/abis/IMech.json
mech_client/abis/IToken.json
mech_client/abis/LockPaymentCondition.base.json
mech_client/abis/LockPaymentCondition.gnosis.json
mech_client/abis/MechMarketplace.json
mech_client/abis/NFTSalesTemplate.base.json
mech_client/abis/NFTSalesTemplate.gnosis.json
mech_client/abis/NeverminedConfig.base.json
mech_client/abis/NeverminedConfig.gnosis.json
mech_client/abis/SubscriptionNFT.base.json
mech_client/abis/SubscriptionNFT.gnosis.json
mech_client/abis/SubscriptionProvider.base.json
mech_client/abis/SubscriptionProvider.gnosis.json
mech_client/abis/SubscriptionToken.base.json
mech_client/abis/TransferNFTCondition.base.json
mech_client/abis/TransferNFTCondition.gnosis.json
mech_client/acn.py
mech_client/cli.py
mech_client/configs/mechs.json
mech_client/delivery.py
mech_client/fetch_ipfs_hash.py
mech_client/helpers/__init__.py
mech_client/helpers/acn/README.md
mech_client/helpers/acn/__init__.py
mech_client/helpers/acn/acn.proto
mech_client/helpers/acn/acn_pb2.py
mech_client/helpers/acn/custom_types.py
mech_client/helpers/acn/dialogues.py
mech_client/helpers/acn/message.py
mech_client/helpers/acn/protocol.yaml
mech_client/helpers/acn/serialization.py
mech_client/helpers/acn/tests/__init__.py
mech_client/helpers/acn/tests/test_acn.py
mech_client/helpers/acn/tests/test_acn_dialogues.py
mech_client-0.14.1.dist-info/LICENSE
mech_client-0.14.1.dist-info/METADATA
mech_client-0.14.1.dist-info/WHEEL
mech_client-0.14.1.dist-info/entry_points.txt
mech_client-0.14.1.dist-info/RECORD
