Metadata-Version: 2.1
Name: mech-client
Version: 0.14.1
Summary: Basic client to interact with a mech
License: Apache-2.0
Author: David Minarsch
Author-email: david.minarsch@googlemail.com
Requires-Python: >=3.10,<4.0
Classifier: License :: OSI Approved :: Apache Software License
Classifier: Programming Language :: Python :: 3
Classifier: Programming Language :: Python :: 3.10
Classifier: Programming Language :: Python :: 3.11
Requires-Dist: asn1crypto (>=1.4.0,<1.5.0)
Requires-Dist: gql (>=3.4.1)
Requires-Dist: open-aea-cli-ipfs (>=1.53.0,<2.0.0)
Requires-Dist: open-aea-ledger-cosmos (>=1.53.0,<2.0.0)
Requires-Dist: open-aea-ledger-ethereum (>=1.53.0,<2.0.0)
Requires-Dist: open-aea[cli] (>=1.53.0,<2.0.0)
Requires-Dist: setuptools (>=77.0.3,<78.0.0)
Requires-Dist: tabulate (>=0.9.0,<0.10.0)
Requires-Dist: websocket-client (>=0.32.0,<1)
